swayblur/__about__.py
swayblur/__init__.py
swayblur/__main__.py
swayblur/blurManager.py
swayblur/output.py
swayblur/paths.py
swayblur-1.1.1.dist-info/LICENSE
swayblur-1.1.1.dist-info/METADATA
swayblur-1.1.1.dist-info/WHEEL
swayblur-1.1.1.dist-info/entry_points.txt
swayblur-1.1.1.dist-info/top_level.txt
swayblur-1.1.1.dist-info/RECORD
