Metadata-Version: 2.1
Name: swayblur
Version: 1.1.1
Summary: Basic sway wallpaper auto-blurring script
Home-page: https://github.com/willpower3309/swayblur
Author: William McKinnon
Author-email: contact@willmckinnon.com
License: MIT
Project-URL: Code, https://github.com/willpower3309/swayblur
Project-URL: Issues, https://github.com/willpower3309/swayblur/issues
Keywords: sway,blur,wallpaper,desktop,ricing
Platform: UNKNOWN
Classifier: Development Status :: 4 - Beta
Classifier: License :: OSI Approved :: MIT License
Classifier: Operating System :: OS Independent
Classifier: Programming Language :: Python
Classifier: Programming Language :: Python :: 3
Classifier: Programming Language :: Python :: 3.6
Classifier: Programming Language :: Python :: 3.7
Classifier: Programming Language :: Python :: 3.8
Classifier: Programming Language :: Python :: 3.9
Requires-Python: >=3.6
License-File: LICENSE
Requires-Dist: importlib-metadata
Requires-Dist: i3ipc
